pip_services4_logic/__init__.py
pip_services4_logic/build/DefaultLogicFactory.py
pip_services4_logic/build/__init__.py
pip_services4_logic/cache/CacheEntry.py
pip_services4_logic/cache/DefaultCacheFactory.py
pip_services4_logic/cache/ICache.py
pip_services4_logic/cache/MemoryCache.py
pip_services4_logic/cache/NullCache.py
pip_services4_logic/cache/__init__.py
pip_services4_logic/lock/DefaultLockFactory.py
pip_services4_logic/lock/ILock.py
pip_services4_logic/lock/Lock.py
pip_services4_logic/lock/MemoryLock.py
pip_services4_logic/lock/NullLock.py
pip_services4_logic/lock/__init__.py
pip_services4_logic/state/DefaultStateStoreFactory.py
pip_services4_logic/state/IStateStore.py
pip_services4_logic/state/MemoryStateStore.py
pip_services4_logic/state/NullStateStore.py
pip_services4_logic/state/StateEntry.py
pip_services4_logic/state/StateValue.py
pip_services4_logic/state/__init__.py
pip_services4_logic-0.0.5.dist-info/LICENSE
pip_services4_logic-0.0.5.dist-info/METADATA
pip_services4_logic-0.0.5.dist-info/WHEEL
pip_services4_logic-0.0.5.dist-info/top_level.txt
pip_services4_logic-0.0.5.dist-info/zip-safe
pip_services4_logic-0.0.5.dist-info/RECORD
